{
  "SAN": {
    "nombre": "Banco Santander",
    "precio": 9.7,
    "sector": "Banca"
  },
  "BBVA": {
    "nombre": "BBVA",
    "precio": 18.68,
    "sector": "Banca"
  },
  "CABK": {
    "nombre": "CaixaBank",
    "precio": 10.36,
    "sector": "Banca"
  },
  "SAB": {
    "nombre": "Banco Sabadell",
    "precio": 3.11,
    "sector": "Banca"
  },
  "BKT": {
    "nombre": "Bankinter",
    "precio": 13.55,
    "sector": "Banca"
  },
  "UNI": {
    "nombre": "Unicaja",
    "precio": 2.57,
    "sector": "Banca"
  },
  "IBE": {
    "nombre": "Iberdrola",
    "precio": 19.4,
    "sector": "Utilities"
  },
  "REP": {
    "nombre": "Repsol",
    "precio": 23.62,
    "sector": "Energía"
  },
  "ENG": {
    "nombre": "Enagás",
    "precio": 14.78,
    "sector": "Utilities"
  },
  "ELE": {
    "nombre": "Endesa",
    "precio": 34.86,
    "sector": "Utilities"
  },
  "SLR": {
    "nombre": "Solaria",
    "precio": 23.33,
    "sector": "Renovables"
  },
  "ANE": {
    "nombre": "Acciona Energía",
    "precio": 21.26,
    "sector": "Renovables"
  },
  "ITX": {
    "nombre": "Inditex",
    "precio": 50.4,
    "sector": "Retail"
  },
  "PUIG": {
    "nombre": "Puig",
    "precio": 17.35,
    "sector": "Lujo/Consumo"
  },
  "FER": {
    "nombre": "Ferrovial",
    "precio": 55.06,
    "sector": "Infraestructuras"
  },
  "ACS": {
    "nombre": "ACS",
    "precio": 107.0,
    "sector": "Construcción"
  },
  "ACX": {
    "nombre": "Acerinox",
    "precio": 12.53,
    "sector": "Acero/Industrial"
  },
  "FDR": {
    "nombre": "Fluidra",
    "precio": 19.61,
    "sector": "Industrial"
  },
  "TEF": {
    "nombre": "Telefónica",
    "precio": 3.72,
    "sector": "Telecom"
  },
  "IAG": {
    "nombre": "IAG",
    "precio": 4.23,
    "sector": "Aerolíneas"
  },
  "AENA": {
    "nombre": "Aena",
    "precio": 25.7,
    "sector": "Infraestructuras"
  },
  "MEL": {
    "nombre": "Meliá Hotels",
    "precio": 9.61,
    "sector": "Turismo"
  },
  "AMS": {
    "nombre": "Amadeus",
    "precio": 50.7,
    "sector": "Tecnología/Turismo"
  },
  "IDR": {
    "nombre": "Indra",
    "precio": 48.02,
    "sector": "Defensa/Tech"
  },
  "MAP": {
    "nombre": "Mapfre",
    "precio": 3.79,
    "sector": "Seguros"
  },
  "GRF": {
    "nombre": "Grifols",
    "precio": 8.96,
    "sector": "Salud"
  },
  "MRL": {
    "nombre": "Merlin Properties",
    "precio": 13.64,
    "sector": "Inmobiliario"
  },
  "COL": {
    "nombre": "Colonial",
    "precio": 5.01,
    "sector": "Inmobiliario"
  },
  "LOG": {
    "nombre": "Logista",
    "precio": 31.4,
    "sector": "Distribución"
  },
  "CLNX": {
    "nombre": "Cellnex",
    "precio": 26.41,
    "sector": "Infraestructuras Telecom"
  },
  "SCYR": {
    "nombre": "Sacyr",
    "precio": 4.19,
    "sector": "Construcción"
  },
  "PHM": {
    "nombre": "Pharma Mar",
    "precio": 89.6,
    "sector": "Salud"
  },
  "ROVI": {
    "nombre": "Laboratorios Rovi",
    "precio": 79.3,
    "sector": "Salud"
  },
  "CIE": {
    "nombre": "CIE Automotive",
    "precio": 27.05,
    "sector": "Automoción"
  }
}