{
  "fecha": "2026-02-03",
  "sesion": "manana",
  "sentimiento": "ALCISTA",
  "recomendaciones": [
    {
      "ranking": 1,
      "ticker": "ITX",
      "nombre": "Inditex",
      "accion": "COMPRA",
      "conviccion": "ALTA",
      "precio_actual": 55.5,
      "entrada": 55.0,
      "stop_loss": 53.9,
      "stop_pct": -2.0,
      "take_profit_1": 58.0,
      "tp1_pct": 4.5,
      "take_profit_2": 60.0,
      "tp2_pct": 8.1,
      "soporte_obvio": 54.0,
      "resistencia_obvia": 56.5,
      "catalizador_tipo": "SECTORIAL",
      "catalizador_desc": "Recuperación del sector retail",
      "catalizador_reversible": false,
      "shorts_pct": 0.5,
      "prob_barrido": "MEDIA",
      "riesgo": "Volatilidad del sector minorista",
      "horizonte_dias": 3
    },
    {
      "ranking": 2,
      "ticker": "ENG",
      "nombre": "Enagás",
      "accion": "COMPRA",
      "conviccion": "MEDIA",
      "precio_actual": 13.94,
      "entrada": 13.8,
      "stop_loss": 13.52,
      "stop_pct": -2.0,
      "take_profit_1": 14.5,
      "tp1_pct": 4.0,
      "take_profit_2": 14.85,
      "tp2_pct": 6.5,
      "soporte_obvio": 13.5,
      "resistencia_obvia": 14.2,
      "catalizador_tipo": "TECNICO",
      "catalizador_desc": "Rebote en soporte técnico",
      "catalizador_reversible": false,
      "shorts_pct": 0.3,
      "prob_barrido": "BAJA",
      "riesgo": "Corrección técnica",
      "horizonte_dias": 4
    },
    {
      "ranking": 3,
      "ticker": "REP",
      "nombre": "Repsol",
      "accion": "COMPRA",
      "conviccion": "MEDIA",
      "precio_actual": 16.36,
      "entrada": 16.2,
      "stop_loss": 15.87,
      "stop_pct": -3.0,
      "take_profit_1": 17.0,
      "tp1_pct": 3.9,
      "take_profit_2": 17.5,
      "tp2_pct": 7.0,
      "soporte_obvio": 16.0,
      "resistencia_obvia": 16.8,
      "catalizador_tipo": "FUNDAMENTAL",
      "catalizador_desc": "Aumento en precios del petróleo",
      "catalizador_reversible": false,
      "shorts_pct": 1.2,
      "prob_barrido": "MEDIA",
      "riesgo": "Volatilidad del mercado petrolero",
      "horizonte_dias": 4
    },
    {
      "ranking": 4,
      "ticker": "IAG",
      "nombre": "International Airlines Group",
      "accion": "COMPRA",
      "conviccion": "BAJA",
      "precio_actual": 5.0,
      "entrada": 4.9,
      "stop_loss": 4.8,
      "stop_pct": -2.0,
      "take_profit_1": 5.3,
      "tp1_pct": 6.0,
      "take_profit_2": 5.5,
      "tp2_pct": 10.0,
      "soporte_obvio": 4.8,
      "resistencia_obvia": 5.2,
      "catalizador_tipo": "GEOPOLITICO",
      "catalizador_desc": "Reapertura de fronteras",
      "catalizador_reversible": true,
      "shorts_pct": 0.8,
      "prob_barrido": "ALTA",
      "riesgo": "Restricciones de viaje",
      "horizonte_dias": 5
    },
    {
      "ranking": 5,
      "ticker": "AENA",
      "nombre": "Aena",
      "accion": "COMPRA",
      "conviccion": "MEDIA",
      "precio_actual": 26.41,
      "entrada": 26.0,
      "stop_loss": 25.48,
      "stop_pct": -3.5,
      "take_profit_1": 27.5,
      "tp1_pct": 4.1,
      "take_profit_2": 28.0,
      "tp2_pct": 6.0,
      "soporte_obvio": 25.5,
      "resistencia_obvia": 27.0,
      "catalizador_tipo": "FUNDAMENTAL",
      "catalizador_desc": "Incremento en el tráfico aéreo",
      "catalizador_reversible": false,
      "shorts_pct": 1.5,
      "prob_barrido": "MEDIA",
      "riesgo": "Controles en aeropuertos",
      "horizonte_dias": 3
    }
  ],
  "evitar": [
    {
      "ticker": "REP",
      "razon": "Elevado ratio de posiciones cortas"
    }
  ]
}